{
    "packageDirectories": [
        {
            "path": "PianoInstrument",
            "package": "PianoPackage",
            "versionName": "ver 0.1",
            "versionNumber": "0.1.0.NEXT",
            "default": true,
            "dependencies": [
                {
                    "package": "AudioPlayerPack",
                    "versionNumber": "0.1.0.LATEST"
                }
            ]
        },
        {
            "path": "AudioPlayerPack",
            "package": "AudioPlayerPack",
            "versionName": "ver 0.1",
            "versionNumber": "0.1.0.LATEST",
            "default": false
        }
    ],
    "name": "Project-3",
    "namespace": "",
    "sfdcLoginUrl": "https://resourceful-moose-q6thfr-dev-ed.my.salesforce.com/",
    "sourceApiVersion": "52.0",
    "packageAliases": {
        "PianoPackage": "0Ho5f0000008OXwCAM",
        "AudioPlayerPack": "0Ho5f0000008OY6CAM",
        "AudioPlayerPack@0.1.0-1": "04t5f000000tv24AAA",
        "PianoPackage@0.1.0-1": "04t5f000000tv6HAAQ"
    }
}